odoo/addons/mrp_production_back_to_draft/README.rst
odoo/addons/mrp_production_back_to_draft/__init__.py
odoo/addons/mrp_production_back_to_draft/__manifest__.py
odoo/addons/mrp_production_back_to_draft/i18n/es.po
odoo/addons/mrp_production_back_to_draft/i18n/it.po
odoo/addons/mrp_production_back_to_draft/i18n/mrp_production_back_to_draft.pot
odoo/addons/mrp_production_back_to_draft/i18n/nl.po
odoo/addons/mrp_production_back_to_draft/i18n/pt_BR.po
odoo/addons/mrp_production_back_to_draft/i18n/tr.po
odoo/addons/mrp_production_back_to_draft/models/__init__.py
odoo/addons/mrp_production_back_to_draft/models/mrp_production.py
odoo/addons/mrp_production_back_to_draft/readme/CONTRIBUTORS.md
odoo/addons/mrp_production_back_to_draft/readme/DESCRIPTION.md
odoo/addons/mrp_production_back_to_draft/static/description/icon.png
odoo/addons/mrp_production_back_to_draft/static/description/index.html
odoo/addons/mrp_production_back_to_draft/tests/__init__.py
odoo/addons/mrp_production_back_to_draft/tests/test_mrp_return_to_draft.py
odoo/addons/mrp_production_back_to_draft/views/mrp_production_views.xml
odoo_addon_mrp_production_back_to_draft-19.0.1.0.1.dist-info/METADATA
odoo_addon_mrp_production_back_to_draft-19.0.1.0.1.dist-info/WHEEL
odoo_addon_mrp_production_back_to_draft-19.0.1.0.1.dist-info/top_level.txt
odoo_addon_mrp_production_back_to_draft-19.0.1.0.1.dist-info/RECORD
